<?xml version="1.0"?>
<config>
    <menu>
        <catalog>
            <children>
                <categories>
                    <children>
                        <reorder>
                            <title>Reorder</title>
                            <children>
                                <reorder_by_id>
                                    <title>by ID ASC</title>
                                    <action>adminhtml/categoriesReorder/byID</action>
                                </reorder_by_id>
                                <reorder_by_name>
                                    <title>by Name ASC</title>
                                    <action>adminhtml/categoriesReorder/byName</action>
                                </reorder_by_name>
                                <reorder_by_rand>
                                    <title>Randomize</title>
                                    <action>adminhtml/categoriesReorder/byRand</action>
                                </reorder_by_rand>
                                <!--<reorder_by_custom>-->
                                    <!--@todo Custom reorder defined in System->Configuration-->
                                    <!--<title>Custom</title>-->
                                    <!--<action>adminhtml/categoriesReorder/byCustom</action>-->
                                <!--</reorder_by_custom>-->
                            </children>
                        </reorder>
                    </children>
                </categories>
            </children>
        </catalog>
    </menu>
    <acl>
        <resources>
            <admin>
                <children>
                    <catalog>
                        <children>
                            <categories>
                                <children>
                                    <zookal_reordercategories translate="title" module="zookal_reordercategories">
                                        <title>Reorder Categories</title>
                                        <sort_order>3000</sort_order>
                                    </zookal_reordercategories>
                                </children>
                            </categories>
                        </children>
                    </catalog>
                </children>
            </admin>
        </resources>
    </acl>
</config>
